{
    "departments": [],
    "contact": {
        "分機": "42425",
        "直撥電話": "03-5742425",
        "傳真電話": "03-5723762",
        "Email": "sls@my.nthu.edu.tw",
        "網頁": "http://www.nsrrc.org.tw/ad/"
    },
    "people": [
        {
            "姓名": "牟中瑜",
            "職稱/職責": "學程主任",
            "分機": "42500",
            "備註": "N/A",
            "Email": "mou@phys.nthu.edu.tw"
        },
        {
            "姓名": "蘇雲良",
            "職稱/職責": "物理組主任",
            "分機": "42799",
            "備註": "N/A",
            "Email": "soo@phys.nthu.edu.tw"
        },
        {
            "姓名": "李志浩",
            "職稱/職責": "工科組主任",
            "分機": "34281",
            "備註": "N/A",
            "Email": "chlee@ess.nthu.edu.tw"
        },
        {
            "姓名": "朱麗安",
            "職稱/職責": "研究助理",
            "分機": "42425",
            "備註": "N/A",
            "Email": "sls@my.nthu.edu.tw"
        }
    ]
}