{
    "departments": [],
    "contact": {
        "分機": "31014、33001",
        "直撥電話": "03-5712861",
        "傳真電話": "03-5743034",
        "Email": "adms@my.nthu.edu.tw",
        "網頁": "https://adms.site.nthu.edu.tw/"
    },
    "people": [
        {
            "姓名": "王潔",
            "職稱/職責": "中心主任",
            "分機": "N/A",
            "備註": "N/A",
            "Email": "janewang@mx.nthu.edu.tw"
        },
        {
            "姓名": "古雅瑄",
            "職稱/職責": "執行秘書",
            "分機": "33212",
            "備註": "R213",
            "Email": "kuyh@mx.nthu.edu.tw"
        },
        {
            "姓名": "曾玉美",
            "職稱/職責": "專案助理",
            "分機": "31300",
            "備註": "R213",
            "Email": "ymtseng@mx.nthu.edu.tw"
        },
        {
            "姓名": "李宜曄",
            "職稱/職責": "組員",
            "分機": "31301",
            "備註": "R213",
            "Email": "iyeh@mx.nthu.edu.tw"
        },
        {
            "姓名": "沈欣穎",
            "職稱/職責": "研究助理",
            "分機": "31302",
            "備註": "R213",
            "Email": "hyshen@mx.nthu.edu.tw"
        },
        {
            "姓名": "王思婷",
            "職稱/職責": "組員",
            "分機": "31385",
            "備註": "R213",
            "Email": "wsihting@mx.nthu.edu.tw"
        },
        {
            "姓名": "曾玉如",
            "職稱/職責": "行政助理",
            "分機": "31398",
            "備註": "R213",
            "Email": "yuju-tseng@mx.nthu.edu.tw"
        },
        {
            "姓名": "陳淑卿",
            "職稱/職責": "助理管理師",
            "分機": "31399",
            "備註": "R213",
            "Email": "gsro@my.nthu.edu.tw"
        },
        {
            "姓名": "彭心儀",
            "職稱/職責": "助理研究員",
            "分機": "33213",
            "備註": "R207",
            "Email": "hy.peng@mx.nthu.edu.tw"
        },
        {
            "姓名": "江姮臻",
            "職稱/職責": "行政助理",
            "分機": "33003",
            "備註": "R207",
            "Email": "hc.chiang@mx.nthu.edu.tw"
        },
        {
            "姓名": "洪芷云",
            "職稱/職責": "研究助理",
            "分機": "33004",
            "備註": "R207",
            "Email": "cy_hung@mx.nthu.edu.tw "
        },
        {
            "姓名": "陳韋芊",
            "職稱/職責": "研究助理",
            "分機": "33005",
            "備註": "R207",
            "Email": "weichienchen@mx.nthu.edu.tw"
        }
    ]
}